sqljson/__init__.py
sqljson/main.py
tests/__init__.py
tests/test_main.py
sqljson-0.1.8.dist-info/LICENSE
sqljson-0.1.8.dist-info/METADATA
sqljson-0.1.8.dist-info/WHEEL
sqljson-0.1.8.dist-info/entry_points.txt
sqljson-0.1.8.dist-info/top_level.txt
sqljson-0.1.8.dist-info/RECORD
